dicomset/config.py
dicomset/utils.py
dicomset/dataset/__init__.py
dicomset/dataset/dataset.py
dicomset/dataset/shared.py
dicomset/dataset/dicom/__init__.py
dicomset/dataset/dicom/ct_series.py
dicomset/dataset/dicom/dicom_dataset.py
dicomset/dataset/dicom/dicom_file.py
dicomset/dataset/dicom/dicom_patient.py
dicomset/dataset/dicom/dicom_series.py
dicomset/dataset/dicom/dicom_study.py
dicomset/dataset/dicom/index.py
dicomset/dataset/dicom/nifti.py
dicomset/dataset/dicom/region_map.py
dicomset/dataset/dicom/region_policy.py
dicomset/dataset/dicom/roi_data.py
dicomset/dataset/dicom/rtdose.py
dicomset/dataset/dicom/rtdose_series.py
dicomset/dataset/dicom/rtplan.py
dicomset/dataset/dicom/rtplan_series.py
dicomset/dataset/dicom/rtstruct.py
dicomset/dataset/dicom/rtstruct_converter.py
dicomset/dataset/dicom/rtstruct_series.py
dicomset/dataset/nifti/__init__.py
dicomset/dataset/nifti/nifti_dataset.py
dicomset/dataset/nifti/nifti_patient.py
dicomset/dataset/nrrd/__init__.py
dicomset/dataset/nrrd/nrrd_dataset.py
dicomset/dataset/nrrd/nrrd_patient.py
dicomset/dataset/other/__init__.py
dicomset/dataset/other/other_dataset.py
dicomset/dataset/other/other_sample.py
dicomset/dataset/training/__init__.py
dicomset/dataset/training/training_dataset.py
dicomset/dataset/training/training_sample.py
dicomset/geometry/__init__.py
dicomset/geometry/box.py
dicomset/geometry/centre.py
dicomset/geometry/extent.py
dicomset/logging/__init__.py
dicomset/metrics/__init__.py
dicomset/metrics/contrast.py
dicomset/metrics/dice.py
dicomset/metrics/distances.py
dicomset/metrics/registration.py
dicomset/metrics/volume.py
dicomset/plotting/__init__.py
dicomset/plotting/plotter.py
dicomset/plotting/results.py
dicomset/plotting/dataset/dicom.py
dicomset/plotting/dataset/nifti.py
dicomset/plotting/dataset/nrrd.py
dicomset/plotting/dataset/training_adaptive.py
dicomset/postprocessing/__init__.py
dicomset/postprocessing/cca.py
dicomset/postprocessing/encode.py
dicomset/postprocessing/interpolation.py
dicomset-0.0.28.dist-info/METADATA
dicomset-0.0.28.dist-info/WHEEL
dicomset-0.0.28.dist-info/top_level.txt
dicomset-0.0.28.dist-info/RECORD
